premod/__init__.py
premod/prepocessing_text.py
premod-2021.12.19.3.dist-info/LICENSE.md
premod-2021.12.19.3.dist-info/METADATA
premod-2021.12.19.3.dist-info/WHEEL
premod-2021.12.19.3.dist-info/top_level.txt
premod-2021.12.19.3.dist-info/RECORD
