Metadata-Version: 2.1
Name: premod
Version: 2021.12.19.3
Summary: preprocessing - modeling
Home-page: https://github.com/RestuLab/premod
Author: andrepradika
Author-email: andrepradika@busoph.id
License: UNKNOWN
Project-URL: Bug Tracker, https://github.com/RestuLab/premod/issues
Platform: UNKNOWN
Classifier: Programming Language :: Python :: 3
Classifier: License :: OSI Approved :: MIT License
Classifier: Operating System :: OS Independent
Requires-Python: >=3.6
License-File: LICENSE.md
